topsis/__init__.py
topsis/topsis.py
topsis_yashika_102303439-1.0.0.dist-info/licenses/LICENSE
topsis_yashika_102303439-1.0.0.dist-info/METADATA
topsis_yashika_102303439-1.0.0.dist-info/WHEEL
topsis_yashika_102303439-1.0.0.dist-info/top_level.txt
topsis_yashika_102303439-1.0.0.dist-info/RECORD
