Metadata-Version: 2.4
Name: Topsis-Yashika-102303439
Version: 1.0.0
Summary: A Python package for TOPSIS method
Author: Yashika
Author-email: yashikagarg1508@gmail.com
Requires-Python: >=3.7
License-File: LICENSE
Requires-Dist: pandas
Requires-Dist: numpy
Dynamic: author
Dynamic: author-email
Dynamic: description
Dynamic: description-content-type
Dynamic: license-file
Dynamic: requires-dist
Dynamic: requires-python
Dynamic: summary
